{
  "slug": "un-chongo-pa-guille",
  "title": "Te pido un chongo, un chongo para guille 🎵",
  "party_owner": "Frente de la cadorcha",
  "intro": "Breve intro de la propuesta integral del partido.",
  "category": "salud",
  "type": "reforma",
  "description":"Lorem ipsum dolor sit amet, consectetur adipiscing elit. Elementum nisl curabitur dolor varius in fames lacus. Ac sed aliquet et maecenas. Nunc vel et magna a, eget penatibus eget. Nisl, eu enim tempus ante. Nulla neque, eget sed libero nec. Sit dolor sed neque mi facilisi massa turpis facilisi. Dolor eget mauris non arcu, pellentesque. Non non ipsum, feugiat pellentesque posuere ipsum pulvinar egestas. Morbi.",
  "original_url": "",
  "other_links": [
    {"name": "lala", "url": "lala.com"}
  ]
}